pycture/__init__.py
pycture/cli.py
pycture/constants.py
pycture/utils.py
pycture-complete.sh
pycture-0.1.0.dist-info/entry_points.txt
pycture-0.1.0.dist-info/LICENSE
pycture-0.1.0.dist-info/WHEEL
pycture-0.1.0.dist-info/METADATA
pycture-0.1.0.dist-info/RECORD
