Metadata-Version: 2.1
Name: pycture
Version: 0.1.0
Summary: A Python CLI for obtaining emojis as files and favicons.
Home-page: https://github.com/joaopalmeiro/pycture
License: MIT
Keywords: pycture,emoji,svg,twemoji,openmoji,cli
Author: João Palmeiro
Author-email: joaommpalmeiro@gmail.com
Requires-Python: >=3.6,<4.0
Classifier: Development Status :: 3 - Alpha
Classifier: Environment :: Console
Classifier: Intended Audience :: Developers
Classifier: Intended Audience :: Information Technology
Classifier: Intended Audience :: Science/Research
Classifier: License :: OSI Approved :: MIT License
Classifier: Natural Language :: English
Classifier: Operating System :: OS Independent
Classifier: Programming Language :: Python :: 3
Classifier: Programming Language :: Python :: 3.6
Classifier: Programming Language :: Python :: 3.7
Classifier: Programming Language :: Python :: 3.8
Classifier: Programming Language :: Python :: 3.9
Classifier: Programming Language :: Python :: Implementation :: CPython
Classifier: Topic :: Terminals
Classifier: Topic :: Text Processing :: Markup :: XML
Classifier: Topic :: Utilities
Requires-Dist: click (>=7.1.2,<8.0.0)
Requires-Dist: defusedxml (>=0.7.1,<0.8.0)
Requires-Dist: importlib-metadata (>=1.0,<2.0); python_version < "3.8"
Requires-Dist: requests (>=2.25.1,<3.0.0)
Project-URL: Bug Tracker, https://github.com/joaopalmeiro/pycture/issues
Project-URL: Repository, https://github.com/joaopalmeiro/pycture
Project-URL: Twitter, https://twitter.com/joaompalmeiro
